gpytorch/__init__.py
gpytorch/beta_features.py
gpytorch/module.py
gpytorch/settings.py
gpytorch/version.py
gpytorch/constraints/__init__.py
gpytorch/constraints/constraints.py
gpytorch/distributions/__init__.py
gpytorch/distributions/delta.py
gpytorch/distributions/distribution.py
gpytorch/distributions/multitask_multivariate_normal.py
gpytorch/distributions/multivariate_normal.py
gpytorch/functions/__init__.py
gpytorch/functions/_log_normal_cdf.py
gpytorch/functions/matern_covariance.py
gpytorch/functions/rbf_covariance.py
gpytorch/kernels/__init__.py
gpytorch/kernels/additive_structure_kernel.py
gpytorch/kernels/arc_kernel.py
gpytorch/kernels/constant_kernel.py
gpytorch/kernels/cosine_kernel.py
gpytorch/kernels/cylindrical_kernel.py
gpytorch/kernels/distributional_input_kernel.py
gpytorch/kernels/gaussian_symmetrized_kl_kernel.py
gpytorch/kernels/grid_interpolation_kernel.py
gpytorch/kernels/grid_kernel.py
gpytorch/kernels/hamming_kernel.py
gpytorch/kernels/index_kernel.py
gpytorch/kernels/inducing_point_kernel.py
gpytorch/kernels/kernel.py
gpytorch/kernels/lcm_kernel.py
gpytorch/kernels/linear_kernel.py
gpytorch/kernels/matern52_kernel_grad.py
gpytorch/kernels/matern_kernel.py
gpytorch/kernels/multi_device_kernel.py
gpytorch/kernels/multitask_kernel.py
gpytorch/kernels/newton_girard_additive_kernel.py
gpytorch/kernels/periodic_kernel.py
gpytorch/kernels/piecewise_polynomial_kernel.py
gpytorch/kernels/polynomial_kernel.py
gpytorch/kernels/polynomial_kernel_grad.py
gpytorch/kernels/product_structure_kernel.py
gpytorch/kernels/rbf_kernel.py
gpytorch/kernels/rbf_kernel_grad.py
gpytorch/kernels/rbf_kernel_gradgrad.py
gpytorch/kernels/rff_kernel.py
gpytorch/kernels/rq_kernel.py
gpytorch/kernels/scale_kernel.py
gpytorch/kernels/spectral_delta_kernel.py
gpytorch/kernels/spectral_mixture_kernel.py
gpytorch/kernels/keops/__init__.py
gpytorch/kernels/keops/keops_kernel.py
gpytorch/kernels/keops/matern_kernel.py
gpytorch/kernels/keops/periodic_kernel.py
gpytorch-1.15.dist-info/licenses/LICENSE
gpytorch-1.15.dist-info/METADATA
gpytorch-1.15.dist-info/WHEEL
gpytorch-1.15.dist-info/top_level.txt
gpytorch-1.15.dist-info/RECORD
