Metadata-Version: 2.4
Name: gpytorch
Version: 1.15
Summary: An implementation of Gaussian Processes in Pytorch
Home-page: https://gpytorch.ai
Author: Jake Gardner, Geoff Pleiss
Author-email: gpleiss@gmail.com
License: MIT
Project-URL: Documentation, https://gpytorch.readthedocs.io
Project-URL: Source, https://github.com/cornellius-gp/gpytorch/
Classifier: Development Status :: 5 - Production/Stable
Classifier: Programming Language :: Python :: 3
Requires-Python: >=3.10
License-File: LICENSE
Requires-Dist: jaxtyping
Requires-Dist: mpmath<=1.3,>=0.19
Requires-Dist: scikit-learn
Requires-Dist: scipy>=1.6.0
Requires-Dist: linear_operator>=0.6
Provides-Extra: dev
Requires-Dist: pre-commit; extra == "dev"
Requires-Dist: setuptools_scm; extra == "dev"
Requires-Dist: twine; extra == "dev"
Requires-Dist: ufmt; extra == "dev"
Provides-Extra: docs
Requires-Dist: ipykernel<=6.17.1; extra == "docs"
Requires-Dist: ipython<=8.6.0; extra == "docs"
Requires-Dist: m2r2<=0.3.3.post2; extra == "docs"
Requires-Dist: nbclient<=0.7.3; extra == "docs"
Requires-Dist: nbformat<=5.8.0; extra == "docs"
Requires-Dist: nbsphinx<=0.9.1; extra == "docs"
Requires-Dist: lxml_html_clean; extra == "docs"
Requires-Dist: platformdirs<=3.2.0; extra == "docs"
Requires-Dist: setuptools_scm<=7.1.0; extra == "docs"
Requires-Dist: sphinx<=6.2.1; extra == "docs"
Requires-Dist: sphinx_autodoc_typehints<=1.23.0; extra == "docs"
Requires-Dist: sphinx_rtd_theme<0.5; extra == "docs"
Provides-Extra: examples
Requires-Dist: ipython; extra == "examples"
Requires-Dist: jupyter; extra == "examples"
Requires-Dist: matplotlib; extra == "examples"
Requires-Dist: scipy; extra == "examples"
Requires-Dist: torchvision; extra == "examples"
Requires-Dist: tqdm; extra == "examples"
Provides-Extra: keops
Requires-Dist: pykeops>=1.1.1; extra == "keops"
Provides-Extra: pyro
Requires-Dist: pyro-ppl>=1.8; extra == "pyro"
Provides-Extra: test
Requires-Dist: flake8==4.0.1; extra == "test"
Requires-Dist: flake8-print==4.0.0; extra == "test"
Requires-Dist: pytest; extra == "test"
Requires-Dist: nbval; extra == "test"
Dynamic: author
Dynamic: author-email
Dynamic: classifier
Dynamic: description
Dynamic: description-content-type
Dynamic: home-page
Dynamic: license
Dynamic: license-file
Dynamic: project-url
Dynamic: provides-extra
Dynamic: requires-dist
Dynamic: requires-python
Dynamic: summary
